io_games/display.py
io_games/draw.py
io_games-0.0.3.dist-info/METADATA
io_games-0.0.3.dist-info/WHEEL
io_games-0.0.3.dist-info/RECORD
